mstt_funasr/__init__.py
mstt_funasr/models.py
mstt_funasr/register.py
mstt_funasr-0.1.0.dist-info/WHEEL
mstt_funasr-0.1.0.dist-info/entry_points.txt
mstt_funasr-0.1.0.dist-info/METADATA
mstt_funasr-0.1.0.dist-info/RECORD
