Metadata-Version: 2.3
Name: mstt-funasr
Version: 0.1.0
Summary: mstt_funasr-A plugin for mstt to add support for FunASR models.
Author: Yunfeng Wang
Author-email: Yunfeng Wang <wyf.brz@gmail.com>
License: Apache-2.0
Requires-Dist: mstt>=0.2.0
Requires-Dist: funasr
Requires-Dist: torchaudio
Requires-Python: >=3.10
